src/videomaster/__init__.py
src/videomaster/assets/blank_frame.png
src/videomaster/cli/__init__.py
src/videomaster/cli/__main__.py
src/videomaster/cli/main.py
src/videomaster/core/__init__.py
src/videomaster/core/demo.py
src/videomaster/core/processor.py
src/videomaster/core/video_effects.py
src/videomaster/core/video_effects_cv2.py
src/videomaster/models/__init__.py
src/videomaster/models/video_processor.py
src/videomaster/utils/__init__.py
src/videomaster/utils/decorators.py
src/videomaster/utils/helpers.py
octopus_videomaster-0.1.4.dist-info/METADATA
octopus_videomaster-0.1.4.dist-info/WHEEL
octopus_videomaster-0.1.4.dist-info/entry_points.txt
octopus_videomaster-0.1.4.dist-info/RECORD
