Metadata-Version: 2.4
Name: octopus-videomaster
Version: 0.1.4
Summary: Octopus video processing module
Author: Evan Bai
Requires-Python: >=3.11
Requires-Dist: build>=1.2.2.post1
Requires-Dist: click<8.2.0
Requires-Dist: ffmpeg-python>=0.2.0
Requires-Dist: moviepy>=1.0.3
Requires-Dist: opencv-python>=4.8.0
Requires-Dist: pydantic>=2.4.0
Requires-Dist: python-dotenv==1.0.1
Requires-Dist: rich==13.7.1
Requires-Dist: twine>=6.1.0
Requires-Dist: typer>=0.15.0
